pqc/demo.py
pqc/_util.py
pqc/__main__.py
pqc/__init__.py
pqc/_lib/libmceliece6688128f_clean.abi3.so
pqc/_lib/libhqc_256_clean.abi3.so
pqc/_lib/libmceliece460896f_clean.abi3.so
pqc/_lib/libsphincs_shake_128f_simple_clean.abi3.so
pqc/_lib/libsphincs_shake_128s_simple_clean.abi3.so
pqc/_lib/libsphincs_shake_256s_simple_clean.abi3.so
pqc/_lib/libmceliece8192128f_clean.abi3.so
pqc/_lib/libsphincs_sha2_128f_simple_clean.abi3.so
pqc/_lib/libkyber768_clean.abi3.so
pqc/_lib/libsphincs_sha2_256f_simple_clean.abi3.so
pqc/_lib/libkyber512_clean.abi3.so
pqc/_lib/libfalcon_1024_clean.abi3.so
pqc/_lib/libsphincs_sha2_256s_simple_clean.abi3.so
pqc/_lib/libfalcon_512_clean.abi3.so
pqc/_lib/libsphincs_sha2_192s_simple_clean.abi3.so
pqc/_lib/libsphincs_shake_192f_simple_clean.abi3.so
pqc/_lib/libdilithium3_clean.abi3.so
pqc/_lib/libdilithium2_clean.abi3.so
pqc/_lib/libmceliece6960119f_clean.abi3.so
pqc/_lib/libhqc_192_clean.abi3.so
pqc/_lib/libkyber1024_clean.abi3.so
pqc/_lib/libsphincs_sha2_192f_simple_clean.abi3.so
pqc/_lib/libsphincs_sha2_128s_simple_clean.abi3.so
pqc/_lib/libhqc_128_clean.abi3.so
pqc/_lib/libsphincs_shake_192s_simple_clean.abi3.so
pqc/_lib/libmceliece348864f_clean.abi3.so
pqc/_lib/libdilithium5_clean.abi3.so
pqc/sign/sphincs_shake_256s_simple.py
pqc/sign/sphincs_sha2_128f_simple.py
pqc/sign/falcon_1024.py
pqc/sign/sphincs_shake_192f_simple.py
pqc/sign/sphincs_sha2_256s_simple.py
pqc/sign/sphincs_sha2_128s_simple.py
pqc/sign/sphincs_shake_128f_simple.py
pqc/sign/dilithium5.py
pqc/sign/sphincs_shake_128s_simple.py
pqc/sign/falcon_512.py
pqc/sign/dilithium3.py
pqc/sign/sphincs_sha2_192s_simple.py
pqc/sign/sphincs_shake_256f_simple.py
pqc/sign/sphincs_sha2_192f_simple.py
pqc/sign/sphincs_sha2_256f_simple.py
pqc/sign/sphincs_shake_192s_simple.py
pqc/sign/dilithium2.py
pqc/kem/kyber512.py
pqc/kem/kyber1024.py
pqc/kem/mceliece8192128.py
pqc/kem/mceliece348864.py
pqc/kem/hqc_128.py
pqc/kem/hqc_192.py
pypqc-0.0.6.2.dist-info/top_level.txt
pypqc-0.0.6.2.dist-info/LICENSE.txt
pypqc-0.0.6.2.dist-info/WHEEL
pypqc-0.0.6.2.dist-info/RECORD
pypqc-0.0.6.2.dist-info/METADATA
