Metadata-Version: 2.1
Name: pypqc
Version: 0.0.6.2
Summary: Python bindings for the "PQClean" post-quantum cryptography library.
Project-URL: Homepage, https://github.com/JamesTheAwesomeDude/pypqc
License-File: LICENSE.txt
Requires-Dist: cffi >=1.0.0 ; platform_python_implementation != "PyPy"
